ibm_gdsc_sdk_software/__init__.py
ibm_gdsc_sdk_software/api_client.py
ibm_gdsc_sdk_software/api_response.py
ibm_gdsc_sdk_software/configuration.py
ibm_gdsc_sdk_software/exceptions.py
ibm_gdsc_sdk_software/py.typed
ibm_gdsc_sdk_software/rest.py
ibm_gdsc_sdk_software/api/__init__.py
ibm_gdsc_sdk_software/api/analytics_events_service_api.py
ibm_gdsc_sdk_software/api/assets_service_api.py
ibm_gdsc_sdk_software/api/audit_service_api.py
ibm_gdsc_sdk_software/api/auth_server_service_api.py
ibm_gdsc_sdk_software/api/cloud_accounts_api.py
ibm_gdsc_sdk_software/api/compliance_accelerator_api.py
ibm_gdsc_sdk_software/api/connections_service_api.py
ibm_gdsc_sdk_software/api/dashboards_service_api.py
ibm_gdsc_sdk_software/api/data_movements_api.py
ibm_gdsc_sdk_software/api/data_resources_api.py
ibm_gdsc_sdk_software/api/data_sensitivities_api.py
ibm_gdsc_sdk_software/api/data_stores_api.py
ibm_gdsc_sdk_software/api/data_vulnerabilities_api.py
ibm_gdsc_sdk_software/api/databootstrapper_service_api.py
ibm_gdsc_sdk_software/api/datamart_processor_service_api.py
ibm_gdsc_sdk_software/api/ecosystem_service_api.py
ibm_gdsc_sdk_software/api/feature_flags_service_api.py
ibm_gdsc_sdk_software/api/group_builder_api.py
ibm_gdsc_sdk_software/api/guardium_connector_api.py
ibm_gdsc_sdk_software/api/health_collector_api.py
ibm_gdsc_sdk_software/api/jumpbox_service_api.py
ibm_gdsc_sdk_software/api/notifications_service_api.py
ibm_gdsc_sdk_software/api/outliers_engine_api.py
ibm_gdsc_sdk_software/api/pipelineconfig_service_api.py
ibm_gdsc_sdk_software/api/policy_builder_api.py
ibm_gdsc_sdk_software/api/qs_data_manager_api.py
ibm_gdsc_sdk_software/api/qs_plugin_manager_api.py
ibm_gdsc_sdk_software/api/qs_policy_manager_api.py
ibm_gdsc_sdk_software/api/reports_runner_api.py
ibm_gdsc_sdk_software/api/reports_service_api.py
ibm_gdsc_sdk_software/api/risk_analytics_controller_api.py
ibm_gdsc_sdk_software/api/risk_analytics_data_processor_api.py
ibm_gdsc_sdk_software/api/risk_analytics_engine_api.py
ibm_gdsc_sdk_software-3.6.1.dist-info/METADATA
ibm_gdsc_sdk_software-3.6.1.dist-info/WHEEL
ibm_gdsc_sdk_software-3.6.1.dist-info/top_level.txt
ibm_gdsc_sdk_software-3.6.1.dist-info/RECORD
