Metadata-Version: 2.1
Name: ibm-gdsc-sdk-software
Version: 3.6.1
Summary: IBM Guardium Data Security Center
Home-page: 
Author: IBM GDSC Team
Author-email: c3cvp8ch@ca.ibm.com
Keywords: OpenAPI,IBM Guardium Data Security Center
Requires-Dist: urllib3 <2.1.0,>=1.25.3
Requires-Dist: python-dateutil
Requires-Dist: pydantic >=2
Requires-Dist: typing-extensions >=4.7.1
